{
	"__comment": "Designed by Harry with Cubik Studio for Distant Lands",
	"textures": {
		"1_0": "block/hardened_clay"
	},
	"elements": [ 	 
		{
			"__comment": "Element",
			"from": [ 0.9213, 0, 9.9713 ],
			"to": [ 7.1213, 0.85, 10.4713 ],
			"faces": {
				"down": { "uv": [ 0, 0, 0.5, 6.2 ], "texture": "#1_0", "rotation": 270 },
				"up": { "uv": [ 0, 0, 0.5, 6.2 ], "texture": "#1_0", "rotation": 90 },
				"north": { "uv": [ 0, 0, 6.2, 0.8500004 ], "texture": "#1_0" },
				"south": { "uv": [ 0, 0, 6.2, 0.8500004 ], "texture": "#1_0" },
				"west": { "uv": [ 0, 0, 0.5, 0.8500004 ], "texture": "#1_0" },
				"east": { "uv": [ 0, 0, 0.5, 0.8500004 ], "texture": "#1_0" }
			}
		},
		{
			"__comment": "Element",
			"from": [ 0.9213, 6.4, 9.7213 ],
			"to": [ 7.1213, 7, 10.3713 ],
			"faces": {
				"down": { "uv": [ 0, 0, 0.65, 6.2 ], "texture": "#1_0", "rotation": 270 },
				"up": { "uv": [ 0, 0, 0.65, 6.2 ], "texture": "#1_0", "rotation": 90 },
				"north": { "uv": [ 0, 0, 6.2, 0.6000004 ], "texture": "#1_0" },
				"south": { "uv": [ 0, 0, 6.2, 0.6000004 ], "texture": "#1_0" },
				"west": { "uv": [ 0, 0, 0.65, 0.6000004 ], "texture": "#1_0" },
				"east": { "uv": [ 0, 0, 0.65, 0.6000004 ], "texture": "#1_0" }
			}
		},
		{
			"__comment": "Element",
			"from": [ 0.9213, 0.65, 10.2213 ],
			"to": [ 7.1213, 6.4, 10.8213 ],
			"faces": {
				"down": { "uv": [ 0, 0, 0.6, 6.2 ], "texture": "#1_0", "rotation": 270 },
				"up": { "uv": [ 0, 0, 0.6, 6.2 ], "texture": "#1_0", "rotation": 90 },
				"north": { "uv": [ 0, 0, 6.2, 5.75 ], "texture": "#1_0" },
				"south": { "uv": [ 0, 0, 6.2, 5.75 ], "texture": "#1_0" },
				"west": { "uv": [ 0, 0, 0.6, 5.75 ], "texture": "#1_0" },
				"east": { "uv": [ 0, 0, 0.6, 5.75 ], "texture": "#1_0" }
			}
		},
		{
			"__comment": "Element",
			"from": [ 0.9213, 0, 3.9713 ],
			"to": [ 7.1213, 0.85, 4.4713 ],
			"faces": {
				"down": { "uv": [ 0, 0, 0.5, 6.2 ], "texture": "#1_0", "rotation": 270 },
				"up": { "uv": [ 0, 0, 0.5, 6.2 ], "texture": "#1_0", "rotation": 90 },
				"north": { "uv": [ 0, 0, 6.2, 0.8500004 ], "texture": "#1_0" },
				"south": { "uv": [ 0, 0, 6.2, 0.8500004 ], "texture": "#1_0" },
				"west": { "uv": [ 0, 0, 0.5, 0.8500004 ], "texture": "#1_0" },
				"east": { "uv": [ 0, 0, 0.5, 0.8500004 ], "texture": "#1_0" }
			}
		},
		{
			"__comment": "Element",
			"from": [ 0.9213, 0.09999999, 4.2213 ],
			"to": [ 7.1213, 0.9499999, 10.2213 ],
			"faces": {
				"down": { "uv": [ 0, 0, 6, 6.2 ], "texture": "#1_0", "rotation": 270 },
				"up": { "uv": [ 0, 0, 6, 6.2 ], "texture": "#1_0", "rotation": 90 },
				"north": { "uv": [ 0, 0, 6.2, 0.8500004 ], "texture": "#1_0" },
				"south": { "uv": [ 0, 0, 6.2, 0.8500004 ], "texture": "#1_0" },
				"west": { "uv": [ 0, 0, 6, 0.8500004 ], "texture": "#1_0" },
				"east": { "uv": [ 0, 0, 6, 0.8500004 ], "texture": "#1_0" }
			}
		},
		{
			"__comment": "Element",
			"from": [ 0.9213, 6.4, 4.0713 ],
			"to": [ 7.1213, 7, 4.7213 ],
			"faces": {
				"down": { "uv": [ 0, 0, 0.65, 6.2 ], "texture": "#1_0", "rotation": 270 },
				"up": { "uv": [ 0, 0, 0.65, 6.2 ], "texture": "#1_0", "rotation": 90 },
				"north": { "uv": [ 0, 0, 6.2, 0.6000004 ], "texture": "#1_0" },
				"south": { "uv": [ 0, 0, 6.2, 0.6000004 ], "texture": "#1_0" },
				"west": { "uv": [ 0, 0, 0.65, 0.6000004 ], "texture": "#1_0" },
				"east": { "uv": [ 0, 0, 0.65, 0.6000004 ], "texture": "#1_0" }
			}
		},
		{
			"__comment": "Element",
			"from": [ 1.4213, 5.15, 4.7213 ],
			"to": [ 6.6213, 8.15, 5.2213 ],
			"faces": {
				"down": { "uv": [ 0, 0, 0.5, 5.2 ], "texture": "#1_0", "rotation": 270 },
				"up": { "uv": [ 0, 0, 0.5, 5.2 ], "texture": "#1_0", "rotation": 90 },
				"north": { "uv": [ 0, 0, 5.2, 3 ], "texture": "#1_0" },
				"south": { "uv": [ 0, 0, 5.2, 3 ], "texture": "#1_0" },
				"west": { "uv": [ 0, 0, 0.5, 3 ], "texture": "#1_0" },
				"east": { "uv": [ 0, 0, 0.5, 3 ], "texture": "#1_0" }
			}
		},
		{
			"__comment": "Element",
			"from": [ 0.9213, 8.15, 4.2213 ],
			"to": [ 1.9213, 8.95, 5.2213 ],
			"faces": {
				"down": { "uv": [ 0, 0, 1, 1 ], "texture": "#1_0", "rotation": 270 },
				"up": { "uv": [ 0, 0, 1, 1 ], "texture": "#1_0", "rotation": 90 },
				"north": { "uv": [ 0, 0, 1, 0.8000002 ], "texture": "#1_0" },
				"south": { "uv": [ 0, 0, 1, 0.8000002 ], "texture": "#1_0" },
				"west": { "uv": [ 0, 0, 1, 0.8000002 ], "texture": "#1_0" },
				"east": { "uv": [ 0, 0, 1, 0.8000002 ], "texture": "#1_0" }
			}
		},
		{
			"__comment": "Element",
			"from": [ 0.9213, 8.15, 9.2213 ],
			"to": [ 1.9213, 8.95, 10.2213 ],
			"faces": {
				"down": { "uv": [ 0, 0, 1, 1 ], "texture": "#1_0", "rotation": 270 },
				"up": { "uv": [ 0, 0, 1, 1 ], "texture": "#1_0", "rotation": 90 },
				"north": { "uv": [ 0, 0, 1, 0.8000002 ], "texture": "#1_0" },
				"south": { "uv": [ 0, 0, 1, 0.8000002 ], "texture": "#1_0" },
				"west": { "uv": [ 0, 0, 1, 0.8000002 ], "texture": "#1_0" },
				"east": { "uv": [ 0, 0, 1, 0.8000002 ], "texture": "#1_0" }
			}
		},
		{
			"__comment": "Element",
			"from": [ 6.1213, 8.15, 9.2213 ],
			"to": [ 7.1213, 8.95, 10.2213 ],
			"faces": {
				"down": { "uv": [ 0, 0, 1, 1 ], "texture": "#1_0", "rotation": 270 },
				"up": { "uv": [ 0, 0, 1, 1 ], "texture": "#1_0", "rotation": 90 },
				"north": { "uv": [ 0, 0, 1, 0.8000002 ], "texture": "#1_0" },
				"south": { "uv": [ 0, 0, 1, 0.8000002 ], "texture": "#1_0" },
				"west": { "uv": [ 0, 0, 1, 0.8000002 ], "texture": "#1_0" },
				"east": { "uv": [ 0, 0, 1, 0.8000002 ], "texture": "#1_0" }
			}
		},
		{
			"__comment": "Element",
			"from": [ 6.1213, 8.15, 4.2213 ],
			"to": [ 7.1213, 8.95, 5.2213 ],
			"faces": {
				"down": { "uv": [ 0, 0, 1, 1 ], "texture": "#1_0", "rotation": 270 },
				"up": { "uv": [ 0, 0, 1, 1 ], "texture": "#1_0", "rotation": 90 },
				"north": { "uv": [ 0, 0, 1, 0.8000002 ], "texture": "#1_0" },
				"south": { "uv": [ 0, 0, 1, 0.8000002 ], "texture": "#1_0" },
				"west": { "uv": [ 0, 0, 1, 0.8000002 ], "texture": "#1_0" },
				"east": { "uv": [ 0, 0, 1, 0.8000002 ], "texture": "#1_0" }
			}
		},
		{
			"__comment": "Element",
			"from": [ 1.4213, 5.15, 9.2213 ],
			"to": [ 6.6213, 8.15, 9.7213 ],
			"faces": {
				"down": { "uv": [ 0, 0, 0.5, 5.2 ], "texture": "#1_0", "rotation": 270 },
				"up": { "uv": [ 0, 0, 0.5, 5.2 ], "texture": "#1_0", "rotation": 90 },
				"north": { "uv": [ 0, 0, 5.2, 3 ], "texture": "#1_0" },
				"south": { "uv": [ 0, 0, 5.2, 3 ], "texture": "#1_0" },
				"west": { "uv": [ 0, 0, 0.5, 3 ], "texture": "#1_0" },
				"east": { "uv": [ 0, 0, 0.5, 3 ], "texture": "#1_0" }
			}
		},
		{
			"__comment": "Element",
			"from": [ 1.9213, 8.15, 4.2213 ],
			"to": [ 6.1213, 8.95, 5.2213 ],
			"faces": {
				"down": { "uv": [ 0, 0, 1, 4.2 ], "texture": "#1_0", "rotation": 270 },
				"up": { "uv": [ 0, 0, 1, 4.2 ], "texture": "#1_0", "rotation": 90 },
				"north": { "uv": [ 0, 0, 4.2, 0.8000002 ], "texture": "#1_0" },
				"south": { "uv": [ 0, 0, 4.2, 0.8000002 ], "texture": "#1_0" },
				"west": { "uv": [ 0, 0, 1, 0.8000002 ], "texture": "#1_0" },
				"east": { "uv": [ 0, 0, 1, 0.8000002 ], "texture": "#1_0" }
			}
		},
		{
			"__comment": "Element",
			"from": [ 1.9213, 8.15, 9.2213 ],
			"to": [ 6.1213, 8.95, 10.2213 ],
			"faces": {
				"down": { "uv": [ 0, 0, 1, 4.2 ], "texture": "#1_0", "rotation": 270 },
				"up": { "uv": [ 0, 0, 1, 4.2 ], "texture": "#1_0", "rotation": 90 },
				"north": { "uv": [ 0, 0, 4.2, 0.8000002 ], "texture": "#1_0" },
				"south": { "uv": [ 0, 0, 4.2, 0.8000002 ], "texture": "#1_0" },
				"west": { "uv": [ 0, 0, 1, 0.8000002 ], "texture": "#1_0" },
				"east": { "uv": [ 0, 0, 1, 0.8000002 ], "texture": "#1_0" }
			}
		},
		{
			"__comment": "Element",
			"from": [ 0.9213, 0.65, 3.6213 ],
			"to": [ 7.1213, 6.4, 4.2213 ],
			"faces": {
				"down": { "uv": [ 0, 0, 0.6, 6.2 ], "texture": "#1_0", "rotation": 270 },
				"up": { "uv": [ 0, 0, 0.6, 6.2 ], "texture": "#1_0", "rotation": 90 },
				"north": { "uv": [ 0, 0, 6.2, 5.75 ], "texture": "#1_0" },
				"south": { "uv": [ 0, 0, 6.2, 5.75 ], "texture": "#1_0" },
				"west": { "uv": [ 0, 0, 0.6, 5.75 ], "texture": "#1_0" },
				"east": { "uv": [ 0, 0, 0.6, 5.75 ], "texture": "#1_0" }
			}
		},
		{
			"__comment": "Element",
			"from": [ 0.6713, 0, 3.9713 ],
			"to": [ 1.1713, 0.85, 10.4713 ],
			"faces": {
				"down": { "uv": [ 0, 0, 0.5, 6.5 ], "texture": "#1_0", "rotation": 180 },
				"up": { "uv": [ 0, 0, 0.5, 6.5 ], "texture": "#1_0", "rotation": 180 },
				"north": { "uv": [ 0, 0, 0.5, 0.8500004 ], "texture": "#1_0" },
				"south": { "uv": [ 0, 0, 0.5, 0.8500004 ], "texture": "#1_0" },
				"west": { "uv": [ 0, 0, 6.5, 0.8500004 ], "texture": "#1_0" },
				"east": { "uv": [ 0, 0, 6.5, 0.8500004 ], "texture": "#1_0" }
			}
		},
		{
			"__comment": "Element",
			"from": [ 0.7713, 6.4, 4.0713 ],
			"to": [ 1.4213, 7, 10.3713 ],
			"faces": {
				"down": { "uv": [ 0, 0, 0.65, 6.3 ], "texture": "#1_0", "rotation": 180 },
				"up": { "uv": [ 0, 0, 0.65, 6.3 ], "texture": "#1_0", "rotation": 180 },
				"north": { "uv": [ 0, 0, 0.65, 0.6000004 ], "texture": "#1_0" },
				"south": { "uv": [ 0, 0, 0.65, 0.6000004 ], "texture": "#1_0" },
				"west": { "uv": [ 0, 0, 6.3, 0.6000004 ], "texture": "#1_0" },
				"east": { "uv": [ 0, 0, 6.3, 0.6000004 ], "texture": "#1_0" }
			}
		},
		{
			"__comment": "Element",
			"from": [ 1.4213, 5.15, 5.2213 ],
			"to": [ 1.9213, 8.15, 9.2213 ],
			"faces": {
				"down": { "uv": [ 0, 0, 0.5, 4 ], "texture": "#1_0", "rotation": 180 },
				"up": { "uv": [ 0, 0, 0.5, 4 ], "texture": "#1_0", "rotation": 180 },
				"north": { "uv": [ 0, 0, 0.5, 3 ], "texture": "#1_0" },
				"south": { "uv": [ 0, 0, 0.5, 3 ], "texture": "#1_0" },
				"west": { "uv": [ 0, 0, 4, 3 ], "texture": "#1_0" },
				"east": { "uv": [ 0, 0, 4, 3 ], "texture": "#1_0" }
			}
		},
		{
			"__comment": "Element",
			"from": [ 0.9213, 8.15, 5.2213 ],
			"to": [ 1.9213, 8.95, 9.2213 ],
			"faces": {
				"down": { "uv": [ 0, 0, 1, 4 ], "texture": "#1_0", "rotation": 180 },
				"up": { "uv": [ 0, 0, 1, 4 ], "texture": "#1_0", "rotation": 180 },
				"north": { "uv": [ 0, 0, 1, 0.8000002 ], "texture": "#1_0" },
				"south": { "uv": [ 0, 0, 1, 0.8000002 ], "texture": "#1_0" },
				"west": { "uv": [ 0, 0, 4, 0.8000002 ], "texture": "#1_0" },
				"east": { "uv": [ 0, 0, 4, 0.8000002 ], "texture": "#1_0" }
			}
		},
		{
			"__comment": "Element",
			"from": [ 6.1213, 8.15, 5.2213 ],
			"to": [ 7.1213, 8.95, 9.2213 ],
			"faces": {
				"down": { "uv": [ 0, 0, 1, 4 ], "texture": "#1_0", "rotation": 180 },
				"up": { "uv": [ 0, 0, 1, 4 ], "texture": "#1_0", "rotation": 180 },
				"north": { "uv": [ 0, 0, 1, 0.8000002 ], "texture": "#1_0" },
				"south": { "uv": [ 0, 0, 1, 0.8000002 ], "texture": "#1_0" },
				"west": { "uv": [ 0, 0, 4, 0.8000002 ], "texture": "#1_0" },
				"east": { "uv": [ 0, 0, 4, 0.8000002 ], "texture": "#1_0" }
			}
		},
		{
			"__comment": "Element",
			"from": [ 6.1213, 5.15, 5.2213 ],
			"to": [ 6.6213, 8.15, 9.2213 ],
			"faces": {
				"down": { "uv": [ 0, 0, 0.5, 4 ], "texture": "#1_0", "rotation": 180 },
				"up": { "uv": [ 0, 0, 0.5, 4 ], "texture": "#1_0", "rotation": 180 },
				"north": { "uv": [ 0, 0, 0.5, 3 ], "texture": "#1_0" },
				"south": { "uv": [ 0, 0, 0.5, 3 ], "texture": "#1_0" },
				"west": { "uv": [ 0, 0, 4, 3 ], "texture": "#1_0" },
				"east": { "uv": [ 0, 0, 4, 3 ], "texture": "#1_0" }
			}
		},
		{
			"__comment": "Element",
			"from": [ 0.3213, 0.65, 4.2213 ],
			"to": [ 0.9213002, 6.4, 10.2213 ],
			"faces": {
				"down": { "uv": [ 0, 0, 0.6, 6 ], "texture": "#1_0", "rotation": 180 },
				"up": { "uv": [ 0, 0, 0.6, 6 ], "texture": "#1_0", "rotation": 180 },
				"north": { "uv": [ 0, 0, 0.6, 5.75 ], "texture": "#1_0" },
				"south": { "uv": [ 0, 0, 0.6, 5.75 ], "texture": "#1_0" },
				"west": { "uv": [ 0, 0, 6, 5.75 ], "texture": "#1_0" },
				"east": { "uv": [ 0, 0, 6, 5.75 ], "texture": "#1_0" }
			}
		},
		{
			"__comment": "Element",
			"from": [ 6.8713, 0, 3.9713 ],
			"to": [ 7.3713, 0.85, 10.4713 ],
			"faces": {
				"down": { "uv": [ 0, 0, 0.5, 6.5 ], "texture": "#1_0", "rotation": 180 },
				"up": { "uv": [ 0, 0, 0.5, 6.5 ], "texture": "#1_0", "rotation": 180 },
				"north": { "uv": [ 0, 0, 0.5, 0.8500004 ], "texture": "#1_0" },
				"south": { "uv": [ 0, 0, 0.5, 0.8500004 ], "texture": "#1_0" },
				"west": { "uv": [ 0, 0, 6.5, 0.8500004 ], "texture": "#1_0" },
				"east": { "uv": [ 0, 0, 6.5, 0.8500004 ], "texture": "#1_0" }
			}
		},
		{
			"__comment": "Element",
			"from": [ 6.6213, 6.4, 4.0713 ],
			"to": [ 7.271299, 7, 10.3713 ],
			"faces": {
				"down": { "uv": [ 0, 0, 0.65, 6.3 ], "texture": "#1_0", "rotation": 180 },
				"up": { "uv": [ 0, 0, 0.65, 6.3 ], "texture": "#1_0", "rotation": 180 },
				"north": { "uv": [ 0, 0, 0.65, 0.6000004 ], "texture": "#1_0" },
				"south": { "uv": [ 0, 0, 0.65, 0.6000004 ], "texture": "#1_0" },
				"west": { "uv": [ 0, 0, 6.3, 0.6000004 ], "texture": "#1_0" },
				"east": { "uv": [ 0, 0, 6.3, 0.6000004 ], "texture": "#1_0" }
			}
		},
		{
			"__comment": "Element",
			"from": [ 7.1213, 0.65, 4.2213 ],
			"to": [ 7.7213, 6.4, 10.2213 ],
			"faces": {
				"down": { "uv": [ 0, 0, 0.6, 6 ], "texture": "#1_0", "rotation": 180 },
				"up": { "uv": [ 0, 0, 0.6, 6 ], "texture": "#1_0", "rotation": 180 },
				"north": { "uv": [ 0, 0, 0.6, 5.75 ], "texture": "#1_0" },
				"south": { "uv": [ 0, 0, 0.6, 5.75 ], "texture": "#1_0" },
				"west": { "uv": [ 0, 0, 6, 5.75 ], "texture": "#1_0" },
				"east": { "uv": [ 0, 0, 6, 5.75 ], "texture": "#1_0" }
			}
		},
		{
			"__comment": "Element",
			"from": [ 7.1213, 0.65, 3.6213 ],
			"to": [ 7.7213, 6.4, 4.2213 ],
			"faces": {
				"down": { "uv": [ 0, 0, 0.6, 0.6000004 ], "texture": "#1_0", "rotation": 180 },
				"up": { "uv": [ 0, 0, 0.6, 0.6000004 ], "texture": "#1_0", "rotation": 180 },
				"north": { "uv": [ 0, 0, 0.6, 5.75 ], "texture": "#1_0" },
				"south": { "uv": [ 0, 0, 0.6, 5.75 ], "texture": "#1_0" },
				"west": { "uv": [ 0, 0, 0.6, 5.75 ], "texture": "#1_0" },
				"east": { "uv": [ 0, 0, 0.6, 5.75 ], "texture": "#1_0" }
			}
		},
		{
			"__comment": "Element",
			"from": [ 0.3213, 0.65, 3.6213 ],
			"to": [ 0.9213002, 6.4, 4.2213 ],
			"faces": {
				"down": { "uv": [ 0, 0, 0.6, 0.6000004 ], "texture": "#1_0", "rotation": 180 },
				"up": { "uv": [ 0, 0, 0.6, 0.6000004 ], "texture": "#1_0", "rotation": 180 },
				"north": { "uv": [ 0, 0, 0.6, 5.75 ], "texture": "#1_0" },
				"south": { "uv": [ 0, 0, 0.6, 5.75 ], "texture": "#1_0" },
				"west": { "uv": [ 0, 0, 0.6, 5.75 ], "texture": "#1_0" },
				"east": { "uv": [ 0, 0, 0.6, 5.75 ], "texture": "#1_0" }
			}
		},
		{
			"__comment": "Element",
			"from": [ 0.3213, 0.65, 10.2213 ],
			"to": [ 0.9213002, 6.4, 10.8213 ],
			"faces": {
				"down": { "uv": [ 0, 0, 0.6, 0.6000004 ], "texture": "#1_0", "rotation": 180 },
				"up": { "uv": [ 0, 0, 0.6, 0.6000004 ], "texture": "#1_0", "rotation": 180 },
				"north": { "uv": [ 0, 0, 0.6, 5.75 ], "texture": "#1_0" },
				"south": { "uv": [ 0, 0, 0.6, 5.75 ], "texture": "#1_0" },
				"west": { "uv": [ 0, 0, 0.6, 5.75 ], "texture": "#1_0" },
				"east": { "uv": [ 0, 0, 0.6, 5.75 ], "texture": "#1_0" }
			}
		},
		{
			"__comment": "Element",
			"from": [ 7.1213, 0.65, 10.2213 ],
			"to": [ 7.7213, 6.4, 10.8213 ],
			"faces": {
				"down": { "uv": [ 0, 0, 0.6, 0.6000004 ], "texture": "#1_0", "rotation": 180 },
				"up": { "uv": [ 0, 0, 0.6, 0.6000004 ], "texture": "#1_0", "rotation": 180 },
				"north": { "uv": [ 0, 0, 0.6, 5.75 ], "texture": "#1_0" },
				"south": { "uv": [ 0, 0, 0.6, 5.75 ], "texture": "#1_0" },
				"west": { "uv": [ 0, 0, 0.6, 5.75 ], "texture": "#1_0" },
				"east": { "uv": [ 0, 0, 0.6, 5.75 ], "texture": "#1_0" }
			}
		},
		{
			"__comment": "Element",
			"from": [ 8.021299, 0.65, 0.2213 ],
			"to": [ 8.921299, 7.1, 1.0213 ],
			"faces": {
				"down": { "uv": [ 0, 0, 0.8, 0.8999996 ], "texture": "#1_0", "rotation": 90 },
				"up": { "uv": [ 0, 0, 0.8, 0.8999996 ], "texture": "#1_0", "rotation": 270 },
				"north": { "uv": [ 0, 0, 0.9, 6.45 ], "texture": "#1_0" },
				"south": { "uv": [ 0, 0, 0.9, 6.45 ], "texture": "#1_0" },
				"west": { "uv": [ 0, 0, 0.8, 6.45 ], "texture": "#1_0" },
				"east": { "uv": [ 0, 0, 0.8, 6.45 ], "texture": "#1_0" }
			}
		},
		{
			"__comment": "Element",
			"from": [ 8.021299, 0.65, 1.0213 ],
			"to": [ 8.921299, 7.1, 7.2213 ],
			"faces": {
				"down": { "uv": [ 0, 0, 0.9, 6.2 ], "texture": "#1_0", "rotation": 180 },
				"up": { "uv": [ 0, 0, 0.9, 6.2 ], "texture": "#1_0", "rotation": 180 },
				"north": { "uv": [ 0, 0, 0.9, 6.45 ], "texture": "#1_0" },
				"south": { "uv": [ 0, 0, 0.9, 6.45 ], "texture": "#1_0" },
				"west": { "uv": [ 0, 0, 6.2, 6.45 ], "texture": "#1_0" },
				"east": { "uv": [ 0, 0, 6.2, 6.45 ], "texture": "#1_0" }
			}
		},
		{
			"__comment": "Element",
			"from": [ 8.9213, 0.65, 7.2213 ],
			"to": [ 14.9213, 7.1, 8.021299 ],
			"faces": {
				"down": { "uv": [ 0, 0, 0.8, 6 ], "texture": "#1_0", "rotation": 90 },
				"up": { "uv": [ 0, 0, 0.8, 6 ], "texture": "#1_0", "rotation": 270 },
				"north": { "uv": [ 0, 0, 6, 6.45 ], "texture": "#1_0" },
				"south": { "uv": [ 0, 0, 6, 6.45 ], "texture": "#1_0" },
				"west": { "uv": [ 0, 0, 0.8, 6.45 ], "texture": "#1_0" },
				"east": { "uv": [ 0, 0, 0.8, 6.45 ], "texture": "#1_0" }
			}
		},
		{
			"__comment": "Element",
			"from": [ 14.9213, 0.65, 7.2213 ],
			"to": [ 15.9213, 7.1, 8.021299 ],
			"faces": {
				"down": { "uv": [ 0, 0, 0.8, 1 ], "texture": "#1_0", "rotation": 90 },
				"up": { "uv": [ 0, 0, 0.8, 1 ], "texture": "#1_0", "rotation": 270 },
				"north": { "uv": [ 0, 0, 1, 6.45 ], "texture": "#1_0" },
				"south": { "uv": [ 0, 0, 1, 6.45 ], "texture": "#1_0" },
				"west": { "uv": [ 0, 0, 0.8, 6.45 ], "texture": "#1_0" },
				"east": { "uv": [ 0, 0, 0.8, 6.45 ], "texture": "#1_0" }
			}
		},
		{
			"__comment": "Element",
			"from": [ 14.9213, 0.65, 0.2213 ],
			"to": [ 15.9213, 7.1, 1.0213 ],
			"faces": {
				"down": { "uv": [ 0, 0, 0.8, 1 ], "texture": "#1_0", "rotation": 90 },
				"up": { "uv": [ 0, 0, 0.8, 1 ], "texture": "#1_0", "rotation": 270 },
				"north": { "uv": [ 0, 0, 1, 6.45 ], "texture": "#1_0" },
				"south": { "uv": [ 0, 0, 1, 6.45 ], "texture": "#1_0" },
				"west": { "uv": [ 0, 0, 0.8, 6.45 ], "texture": "#1_0" },
				"east": { "uv": [ 0, 0, 0.8, 6.45 ], "texture": "#1_0" }
			}
		},
		{
			"__comment": "Element",
			"from": [ 8.521299, 7.1, 0.7213 ],
			"to": [ 15.3213, 7.65, 1.5213 ],
			"faces": {
				"down": { "uv": [ 0, 0, 0.8, 6.8 ], "texture": "#1_0", "rotation": 90 },
				"up": { "uv": [ 0, 0, 0.8, 6.8 ], "texture": "#1_0", "rotation": 270 },
				"north": { "uv": [ 0, 0, 6.8, 0.5500002 ], "texture": "#1_0" },
				"south": { "uv": [ 0, 0, 6.8, 0.5500002 ], "texture": "#1_0" },
				"west": { "uv": [ 0, 0, 0.8, 0.5500002 ], "texture": "#1_0" },
				"east": { "uv": [ 0, 0, 0.8, 0.5500002 ], "texture": "#1_0" }
			}
		},
		{
			"__comment": "Element",
			"from": [ 8.521299, 7.1, 1.3213 ],
			"to": [ 9.421299, 7.65, 6.9213 ],
			"faces": {
				"down": { "uv": [ 0, 0, 0.9, 5.6 ], "texture": "#1_0", "rotation": 180 },
				"up": { "uv": [ 0, 0, 0.9, 5.6 ], "texture": "#1_0", "rotation": 180 },
				"north": { "uv": [ 0, 0, 0.9, 0.5500002 ], "texture": "#1_0" },
				"south": { "uv": [ 0, 0, 0.9, 0.5500002 ], "texture": "#1_0" },
				"west": { "uv": [ 0, 0, 5.6, 0.5500002 ], "texture": "#1_0" },
				"east": { "uv": [ 0, 0, 5.6, 0.5500002 ], "texture": "#1_0" }
			}
		},
		{
			"__comment": "Element",
			"from": [ 8.521299, 7.1, 6.7213 ],
			"to": [ 15.3213, 7.65, 7.521298 ],
			"faces": {
				"down": { "uv": [ 0, 0, 0.8, 6.8 ], "texture": "#1_0", "rotation": 90 },
				"up": { "uv": [ 0, 0, 0.8, 6.8 ], "texture": "#1_0", "rotation": 270 },
				"north": { "uv": [ 0, 0, 6.8, 0.5500002 ], "texture": "#1_0" },
				"south": { "uv": [ 0, 0, 6.8, 0.5500002 ], "texture": "#1_0" },
				"west": { "uv": [ 0, 0, 0.8, 0.5500002 ], "texture": "#1_0" },
				"east": { "uv": [ 0, 0, 0.8, 0.5500002 ], "texture": "#1_0" }
			}
		},
		{
			"__comment": "Element",
			"from": [ 8.021299, 0.65, 7.2213 ],
			"to": [ 8.921299, 7.1, 8.021299 ],
			"faces": {
				"down": { "uv": [ 0, 0, 0.8, 0.8999996 ], "texture": "#1_0", "rotation": 90 },
				"up": { "uv": [ 0, 0, 0.8, 0.8999996 ], "texture": "#1_0", "rotation": 270 },
				"north": { "uv": [ 0, 0, 0.9, 6.45 ], "texture": "#1_0" },
				"south": { "uv": [ 0, 0, 0.9, 6.45 ], "texture": "#1_0" },
				"west": { "uv": [ 0, 0, 0.8, 6.45 ], "texture": "#1_0" },
				"east": { "uv": [ 0, 0, 0.8, 6.45 ], "texture": "#1_0" }
			}
		},
		{
			"__comment": "Element",
			"from": [ 8.9213, 0.65, 0.2213 ],
			"to": [ 14.9213, 7.1, 1.0213 ],
			"faces": {
				"down": { "uv": [ 0, 0, 0.8, 6 ], "texture": "#1_0", "rotation": 90 },
				"up": { "uv": [ 0, 0, 0.8, 6 ], "texture": "#1_0", "rotation": 270 },
				"north": { "uv": [ 0, 0, 6, 6.45 ], "texture": "#1_0" },
				"south": { "uv": [ 0, 0, 6, 6.45 ], "texture": "#1_0" },
				"west": { "uv": [ 0, 0, 0.8, 6.45 ], "texture": "#1_0" },
				"east": { "uv": [ 0, 0, 0.8, 6.45 ], "texture": "#1_0" }
			}
		},
		{
			"__comment": "Element",
			"from": [ 9.021299, 10.25, 2.0213 ],
			"to": [ 9.921299, 11.1, 6.2213 ],
			"faces": {
				"down": { "uv": [ 0, 0, 0.9, 4.2 ], "texture": "#1_0", "rotation": 180 },
				"up": { "uv": [ 0, 0, 0.9, 4.2 ], "texture": "#1_0", "rotation": 180 },
				"north": { "uv": [ 0, 0, 0.9, 0.8500004 ], "texture": "#1_0" },
				"south": { "uv": [ 0, 0, 0.9, 0.8500004 ], "texture": "#1_0" },
				"west": { "uv": [ 0, 0, 4.2, 0.8500004 ], "texture": "#1_0" },
				"east": { "uv": [ 0, 0, 4.2, 0.8500004 ], "texture": "#1_0" }
			}
		},
		{
			"__comment": "Element",
			"from": [ 9.4213, 7.2, 1.5213 ],
			"to": [ 9.9213, 10.65, 6.7213 ],
			"faces": {
				"down": { "uv": [ 0, 0, 0.5, 5.2 ], "texture": "#1_0", "rotation": 180 },
				"up": { "uv": [ 0, 0, 0.5, 5.2 ], "texture": "#1_0", "rotation": 180 },
				"north": { "uv": [ 0, 0, 0.5, 3.45 ], "texture": "#1_0" },
				"south": { "uv": [ 0, 0, 0.5, 3.45 ], "texture": "#1_0" },
				"west": { "uv": [ 0, 0, 5.2, 3.45 ], "texture": "#1_0" },
				"east": { "uv": [ 0, 0, 5.2, 3.45 ], "texture": "#1_0" }
			}
		},
		{
			"__comment": "Element",
			"from": [ 9.9213, 7.2, 6.2213 ],
			"to": [ 13.9213, 10.65, 6.7213 ],
			"faces": {
				"down": { "uv": [ 0, 0, 0.5, 4 ], "texture": "#1_0", "rotation": 90 },
				"up": { "uv": [ 0, 0, 0.5, 4 ], "texture": "#1_0", "rotation": 270 },
				"north": { "uv": [ 0, 0, 4, 3.45 ], "texture": "#1_0" },
				"south": { "uv": [ 0, 0, 4, 3.45 ], "texture": "#1_0" },
				"west": { "uv": [ 0, 0, 0.5, 3.45 ], "texture": "#1_0" },
				"east": { "uv": [ 0, 0, 0.5, 3.45 ], "texture": "#1_0" }
			}
		},
		{
			"__comment": "Element",
			"from": [ 13.9213, 7.2, 1.5213 ],
			"to": [ 14.4213, 10.65, 6.7213 ],
			"faces": {
				"down": { "uv": [ 0, 0, 0.5, 5.2 ], "texture": "#1_0", "rotation": 180 },
				"up": { "uv": [ 0, 0, 0.5, 5.2 ], "texture": "#1_0", "rotation": 180 },
				"north": { "uv": [ 0, 0, 0.5, 3.45 ], "texture": "#1_0" },
				"south": { "uv": [ 0, 0, 0.5, 3.45 ], "texture": "#1_0" },
				"west": { "uv": [ 0, 0, 5.2, 3.45 ], "texture": "#1_0" },
				"east": { "uv": [ 0, 0, 5.2, 3.45 ], "texture": "#1_0" }
			}
		},
		{
			"__comment": "Element",
			"from": [ 9.9213, 7.2, 1.5213 ],
			"to": [ 13.9213, 10.65, 1.9213 ],
			"faces": {
				"down": { "uv": [ 0, 0, 0.4, 4 ], "texture": "#1_0", "rotation": 90 },
				"up": { "uv": [ 0, 0, 0.4, 4 ], "texture": "#1_0", "rotation": 270 },
				"north": { "uv": [ 0, 0, 4, 3.45 ], "texture": "#1_0" },
				"south": { "uv": [ 0, 0, 4, 3.45 ], "texture": "#1_0" },
				"west": { "uv": [ 0, 0, 0.4, 3.45 ], "texture": "#1_0" },
				"east": { "uv": [ 0, 0, 0.4, 3.45 ], "texture": "#1_0" }
			}
		},
		{
			"__comment": "Element",
			"from": [ 9.021299, 10.25, 1.1213 ],
			"to": [ 9.921299, 11.1, 2.0213 ],
			"faces": {
				"down": { "uv": [ 0, 0, 0.9, 0.8999996 ], "texture": "#1_0", "rotation": 180 },
				"up": { "uv": [ 0, 0, 0.9, 0.8999996 ], "texture": "#1_0", "rotation": 180 },
				"north": { "uv": [ 0, 0, 0.9, 0.8500004 ], "texture": "#1_0" },
				"south": { "uv": [ 0, 0, 0.9, 0.8500004 ], "texture": "#1_0" },
				"west": { "uv": [ 0, 0, 0.9, 0.8500004 ], "texture": "#1_0" },
				"east": { "uv": [ 0, 0, 0.9, 0.8500004 ], "texture": "#1_0" }
			}
		},
		{
			"__comment": "Element",
			"from": [ 9.9213, 10.25, 1.1213 ],
			"to": [ 13.9213, 11.1, 2.0213 ],
			"faces": {
				"down": { "uv": [ 0, 0, 0.9, 4 ], "texture": "#1_0", "rotation": 90 },
				"up": { "uv": [ 0, 0, 0.9, 4 ], "texture": "#1_0", "rotation": 270 },
				"north": { "uv": [ 0, 0, 4, 0.8500004 ], "texture": "#1_0" },
				"south": { "uv": [ 0, 0, 4, 0.8500004 ], "texture": "#1_0" },
				"west": { "uv": [ 0, 0, 0.9, 0.8500004 ], "texture": "#1_0" },
				"east": { "uv": [ 0, 0, 0.9, 0.8500004 ], "texture": "#1_0" }
			}
		},
		{
			"__comment": "Element",
			"from": [ 13.9213, 10.25, 1.1213 ],
			"to": [ 14.8213, 11.1, 2.0213 ],
			"faces": {
				"down": { "uv": [ 0, 0, 0.9, 0.8999996 ], "texture": "#1_0", "rotation": 180 },
				"up": { "uv": [ 0, 0, 0.9, 0.8999996 ], "texture": "#1_0", "rotation": 180 },
				"north": { "uv": [ 0, 0, 0.9, 0.8500004 ], "texture": "#1_0" },
				"south": { "uv": [ 0, 0, 0.9, 0.8500004 ], "texture": "#1_0" },
				"west": { "uv": [ 0, 0, 0.9, 0.8500004 ], "texture": "#1_0" },
				"east": { "uv": [ 0, 0, 0.9, 0.8500004 ], "texture": "#1_0" }
			}
		},
		{
			"__comment": "Element",
			"from": [ 13.9213, 10.25, 2.0213 ],
			"to": [ 14.8213, 11.1, 6.2213 ],
			"faces": {
				"down": { "uv": [ 0, 0, 0.9, 4.2 ], "texture": "#1_0", "rotation": 180 },
				"up": { "uv": [ 0, 0, 0.9, 4.2 ], "texture": "#1_0", "rotation": 180 },
				"north": { "uv": [ 0, 0, 0.9, 0.8500004 ], "texture": "#1_0" },
				"south": { "uv": [ 0, 0, 0.9, 0.8500004 ], "texture": "#1_0" },
				"west": { "uv": [ 0, 0, 4.2, 0.8500004 ], "texture": "#1_0" },
				"east": { "uv": [ 0, 0, 4.2, 0.8500004 ], "texture": "#1_0" }
			}
		},
		{
			"__comment": "Element",
			"from": [ 13.9213, 10.25, 6.2213 ],
			"to": [ 14.8213, 11.1, 7.121298 ],
			"faces": {
				"down": { "uv": [ 0, 0, 0.9, 0.8999996 ], "texture": "#1_0", "rotation": 180 },
				"up": { "uv": [ 0, 0, 0.9, 0.8999996 ], "texture": "#1_0", "rotation": 180 },
				"north": { "uv": [ 0, 0, 0.9, 0.8500004 ], "texture": "#1_0" },
				"south": { "uv": [ 0, 0, 0.9, 0.8500004 ], "texture": "#1_0" },
				"west": { "uv": [ 0, 0, 0.9, 0.8500004 ], "texture": "#1_0" },
				"east": { "uv": [ 0, 0, 0.9, 0.8500004 ], "texture": "#1_0" }
			}
		},
		{
			"__comment": "Element",
			"from": [ 9.9213, 10.25, 6.2213 ],
			"to": [ 13.9213, 11.1, 7.121298 ],
			"faces": {
				"down": { "uv": [ 0, 0, 0.9, 4 ], "texture": "#1_0", "rotation": 90 },
				"up": { "uv": [ 0, 0, 0.9, 4 ], "texture": "#1_0", "rotation": 270 },
				"north": { "uv": [ 0, 0, 4, 0.8500004 ], "texture": "#1_0" },
				"south": { "uv": [ 0, 0, 4, 0.8500004 ], "texture": "#1_0" },
				"west": { "uv": [ 0, 0, 0.9, 0.8500004 ], "texture": "#1_0" },
				"east": { "uv": [ 0, 0, 0.9, 0.8500004 ], "texture": "#1_0" }
			}
		},
		{
			"__comment": "Element",
			"from": [ 9.021299, 10.25, 6.2213 ],
			"to": [ 9.921299, 11.1, 7.121298 ],
			"faces": {
				"down": { "uv": [ 0, 0, 0.9, 0.8999996 ], "texture": "#1_0", "rotation": 180 },
				"up": { "uv": [ 0, 0, 0.9, 0.8999996 ], "texture": "#1_0", "rotation": 180 },
				"north": { "uv": [ 0, 0, 0.9, 0.8500004 ], "texture": "#1_0" },
				"south": { "uv": [ 0, 0, 0.9, 0.8500004 ], "texture": "#1_0" },
				"west": { "uv": [ 0, 0, 0.9, 0.8500004 ], "texture": "#1_0" },
				"east": { "uv": [ 0, 0, 0.9, 0.8500004 ], "texture": "#1_0" }
			}
		},
		{
			"__comment": "Element",
			"from": [ 14.4213, 7.1, 1.2213 ],
			"to": [ 15.3213, 7.65, 6.9213 ],
			"faces": {
				"down": { "uv": [ 0, 0, 0.9, 5.7 ], "texture": "#1_0", "rotation": 180 },
				"up": { "uv": [ 0, 0, 0.9, 5.7 ], "texture": "#1_0", "rotation": 180 },
				"north": { "uv": [ 0, 0, 0.9, 0.5500002 ], "texture": "#1_0" },
				"south": { "uv": [ 0, 0, 0.9, 0.5500002 ], "texture": "#1_0" },
				"west": { "uv": [ 0, 0, 5.7, 0.5500002 ], "texture": "#1_0" },
				"east": { "uv": [ 0, 0, 5.7, 0.5500002 ], "texture": "#1_0" }
			}
		},
		{
			"__comment": "Element",
			"from": [ 14.9213, 0.65, 1.0213 ],
			"to": [ 15.9213, 7.1, 7.2213 ],
			"faces": {
				"down": { "uv": [ 0, 0, 1, 6.2 ], "texture": "#1_0", "rotation": 180 },
				"up": { "uv": [ 0, 0, 1, 6.2 ], "texture": "#1_0", "rotation": 180 },
				"north": { "uv": [ 0, 0, 1, 6.45 ], "texture": "#1_0" },
				"south": { "uv": [ 0, 0, 1, 6.45 ], "texture": "#1_0" },
				"west": { "uv": [ 0, 0, 6.2, 6.45 ], "texture": "#1_0" },
				"east": { "uv": [ 0, 0, 6.2, 6.45 ], "texture": "#1_0" }
			}
		},
		{
			"__comment": "Element",
			"from": [ 8.4213, 0.09999999, 7.0213 ],
			"to": [ 15.5213, 0.9499999, 7.7213 ],
			"faces": {
				"down": { "uv": [ 0, 0, 0.7, 7.1 ], "texture": "#1_0", "rotation": 90 },
				"up": { "uv": [ 0, 0, 0.7, 7.1 ], "texture": "#1_0", "rotation": 270 },
				"north": { "uv": [ 0, 0, 7.1, 0.8500004 ], "texture": "#1_0" },
				"south": { "uv": [ 0, 0, 7.1, 0.8500004 ], "texture": "#1_0" },
				"west": { "uv": [ 0, 0, 0.7, 0.8500004 ], "texture": "#1_0" },
				"east": { "uv": [ 0, 0, 0.7, 0.8500004 ], "texture": "#1_0" }
			}
		},
		{
			"__comment": "Element",
			"from": [ 8.4213, 0.09999999, 0.5213 ],
			"to": [ 15.5213, 0.9499999, 1.2213 ],
			"faces": {
				"down": { "uv": [ 0, 0, 0.7, 7.1 ], "texture": "#1_0", "rotation": 90 },
				"up": { "uv": [ 0, 0, 0.7, 7.1 ], "texture": "#1_0", "rotation": 270 },
				"north": { "uv": [ 0, 0, 7.1, 0.8500004 ], "texture": "#1_0" },
				"south": { "uv": [ 0, 0, 7.1, 0.8500004 ], "texture": "#1_0" },
				"west": { "uv": [ 0, 0, 0.7, 0.8500004 ], "texture": "#1_0" },
				"east": { "uv": [ 0, 0, 0.7, 0.8500004 ], "texture": "#1_0" }
			}
		},
		{
			"__comment": "Element",
			"from": [ 8.8213, 0.2, 1.0213 ],
			"to": [ 14.9213, 1.05, 7.2213 ],
			"faces": {
				"down": { "uv": [ 0, 0, 6.1, 6.2 ], "texture": "#1_0", "rotation": 180 },
				"up": { "uv": [ 0, 0, 6.1, 6.2 ], "texture": "#1_0", "rotation": 180 },
				"north": { "uv": [ 0, 0, 6.1, 0.8500004 ], "texture": "#1_0" },
				"south": { "uv": [ 0, 0, 6.1, 0.8500004 ], "texture": "#1_0" },
				"west": { "uv": [ 0, 0, 6.2, 0.8500004 ], "texture": "#1_0" },
				"east": { "uv": [ 0, 0, 6.2, 0.8500004 ], "texture": "#1_0" }
			}
		},
		{
			"__comment": "Element",
			"from": [ 14.6213, 0.09999999, 1.0213 ],
			"to": [ 15.5213, 0.9499999, 7.2213 ],
			"faces": {
				"down": { "uv": [ 0, 0, 0.9, 6.2 ], "texture": "#1_0", "rotation": 180 },
				"up": { "uv": [ 0, 0, 0.9, 6.2 ], "texture": "#1_0", "rotation": 180 },
				"north": { "uv": [ 0, 0, 0.9, 0.8500004 ], "texture": "#1_0" },
				"south": { "uv": [ 0, 0, 0.9, 0.8500004 ], "texture": "#1_0" },
				"west": { "uv": [ 0, 0, 6.2, 0.8500004 ], "texture": "#1_0" },
				"east": { "uv": [ 0, 0, 6.2, 0.8500004 ], "texture": "#1_0" }
			}
		},
		{
			"__comment": "Element",
			"from": [ 8.4213, 0.09999999, 1.0213 ],
			"to": [ 9.3213, 0.9499999, 7.2213 ],
			"faces": {
				"down": { "uv": [ 0, 0, 0.9, 6.2 ], "texture": "#1_0", "rotation": 180 },
				"up": { "uv": [ 0, 0, 0.9, 6.2 ], "texture": "#1_0", "rotation": 180 },
				"north": { "uv": [ 0, 0, 0.9, 0.8500004 ], "texture": "#1_0" },
				"south": { "uv": [ 0, 0, 0.9, 0.8500004 ], "texture": "#1_0" },
				"west": { "uv": [ 0, 0, 6.2, 0.8500004 ], "texture": "#1_0" },
				"east": { "uv": [ 0, 0, 6.2, 0.8500004 ], "texture": "#1_0" }
			}
		},
		{
			"__comment": "Element",
			"from": [ 7.18, 5.1, 14.2594 ],
			"to": [ 7.63, 5.7, 18.8594 ],
			"rotation": { "origin": [ -1.27002, 7, 8.85938 ], "axis": "y", "angle": 22.5 },
			"faces": {
				"down": { "uv": [ 0, 0, 0.65, 6.2 ], "texture": "#1_0", "rotation": 180 },
				"up": { "uv": [ 0, 0, 0.65, 6.2 ], "texture": "#1_0", "rotation": 180 },
				"north": { "uv": [ 0, 0, 0.65, 0.6000004 ], "texture": "#1_0" },
				"south": { "uv": [ 0, 0, 0.65, 0.6000004 ], "texture": "#1_0" },
				"west": { "uv": [ 0, 0, 6.2, 0.6000004 ], "texture": "#1_0" },
				"east": { "uv": [ 0, 0, 6.2, 0.6000004 ], "texture": "#1_0" }
			}
		},
		{
			"__comment": "Element",
			"from": [ 7.3713, 0, 14.1213 ],
			"to": [ 7.8213, 0.6, 19.3213 ],
			"rotation": { "origin": [ -1.07868, 1.9, 9.32132 ], "axis": "y", "angle": 22.5 },
			"faces": {
				"down": { "uv": [ 0, 0, 0.65, 6.2 ], "texture": "#1_0", "rotation": 180 },
				"up": { "uv": [ 0, 0, 0.65, 6.2 ], "texture": "#1_0", "rotation": 180 },
				"north": { "uv": [ 0, 0, 0.65, 0.6000004 ], "texture": "#1_0" },
				"south": { "uv": [ 0, 0, 0.65, 0.6000004 ], "texture": "#1_0" },
				"west": { "uv": [ 0, 0, 6.2, 0.6000004 ], "texture": "#1_0" },
				"east": { "uv": [ 0, 0, 6.2, 0.6000004 ], "texture": "#1_0" }
			}
		},
		{
			"__comment": "Element",
			"from": [ 11.4713, 0, 12.5213 ],
			"to": [ 11.9213, 0.6, 17.3213 ],
			"rotation": { "origin": [ 3.52132, 1.9, 6.82132 ], "axis": "y", "angle": 22.5 },
			"faces": {
				"down": { "uv": [ 0, 0, 0.65, 6.2 ], "texture": "#1_0", "rotation": 180 },
				"up": { "uv": [ 0, 0, 0.65, 6.2 ], "texture": "#1_0", "rotation": 180 },
				"north": { "uv": [ 0, 0, 0.65, 0.6000004 ], "texture": "#1_0" },
				"south": { "uv": [ 0, 0, 0.65, 0.6000004 ], "texture": "#1_0" },
				"west": { "uv": [ 0, 0, 6.2, 0.6000004 ], "texture": "#1_0" },
				"east": { "uv": [ 0, 0, 6.2, 0.6000004 ], "texture": "#1_0" }
			}
		},
		{
			"__comment": "Element",
			"from": [ 11.9213, 4.65, 14.6213 ],
			"to": [ 12.0213, 7.15, 18.8213 ],
			"rotation": { "origin": [ -1.07868, 7, 9.32132 ], "axis": "y", "angle": 22.5 },
			"faces": {
				"down": { "uv": [ 0, 0, 0.5, 5.2 ], "texture": "#1_0", "rotation": 180 },
				"up": { "uv": [ 0, 0, 0.5, 5.2 ], "texture": "#1_0", "rotation": 180 },
				"north": { "uv": [ 0, 0, 0.5, 3 ], "texture": "#1_0" },
				"south": { "uv": [ 0, 0, 0.5, 3 ], "texture": "#1_0" },
				"west": { "uv": [ 0, 0, 5.2, 3 ], "texture": "#1_0" },
				"east": { "uv": [ 0, 0, 5.2, 3 ], "texture": "#1_0" }
			}
		},
		{
			"__comment": "Element",
			"from": [ 11.9213, 6.95, 14.2213 ],
			"to": [ 12.4213, 7.65, 14.6213 ],
			"rotation": { "origin": [ -1.07868, 6.6, 9.32132 ], "axis": "y", "angle": 22.5 },
			"faces": {
				"down": { "uv": [ 0, 0, 1, 1 ], "texture": "#1_0", "rotation": 180 },
				"up": { "uv": [ 0, 0, 1, 1 ], "texture": "#1_0", "rotation": 180 },
				"north": { "uv": [ 0, 0, 1, 0.8000002 ], "texture": "#1_0" },
				"south": { "uv": [ 0, 0, 1, 0.8000002 ], "texture": "#1_0" },
				"west": { "uv": [ 0, 0, 1, 0.8000002 ], "texture": "#1_0" },
				"east": { "uv": [ 0, 0, 1, 0.8000002 ], "texture": "#1_0" }
			}
		},
		{
			"__comment": "Element",
			"from": [ 7.3213, 6.95, 14.2213 ],
			"to": [ 7.9213, 7.65, 14.6213 ],
			"rotation": { "origin": [ -1.07868, 6.6, 9.32132 ], "axis": "y", "angle": 22.5 },
			"faces": {
				"down": { "uv": [ 0, 0, 1, 1 ], "texture": "#1_0", "rotation": 180 },
				"up": { "uv": [ 0, 0, 1, 1 ], "texture": "#1_0", "rotation": 180 },
				"north": { "uv": [ 0, 0, 1, 0.8000002 ], "texture": "#1_0" },
				"south": { "uv": [ 0, 0, 1, 0.8000002 ], "texture": "#1_0" },
				"west": { "uv": [ 0, 0, 1, 0.8000002 ], "texture": "#1_0" },
				"east": { "uv": [ 0, 0, 1, 0.8000002 ], "texture": "#1_0" }
			}
		},
		{
			"__comment": "Element",
			"from": [ 7.3213, 6.95, 18.8213 ],
			"to": [ 7.9213, 7.65, 19.3213 ],
			"rotation": { "origin": [ -1.07868, 6.6, 9.32132 ], "axis": "y", "angle": 22.5 },
			"faces": {
				"down": { "uv": [ 0, 0, 1, 1 ], "texture": "#1_0", "rotation": 180 },
				"up": { "uv": [ 0, 0, 1, 1 ], "texture": "#1_0", "rotation": 180 },
				"north": { "uv": [ 0, 0, 1, 0.8000002 ], "texture": "#1_0" },
				"south": { "uv": [ 0, 0, 1, 0.8000002 ], "texture": "#1_0" },
				"west": { "uv": [ 0, 0, 1, 0.8000002 ], "texture": "#1_0" },
				"east": { "uv": [ 0, 0, 1, 0.8000002 ], "texture": "#1_0" }
			}
		},
		{
			"__comment": "Element",
			"from": [ 11.9213, 6.95, 18.8213 ],
			"to": [ 12.4213, 7.65, 19.3213 ],
			"rotation": { "origin": [ -1.07868, 6.6, 9.32132 ], "axis": "y", "angle": 22.5 },
			"faces": {
				"down": { "uv": [ 0, 0, 1, 1 ], "texture": "#1_0", "rotation": 180 },
				"up": { "uv": [ 0, 0, 1, 1 ], "texture": "#1_0", "rotation": 180 },
				"north": { "uv": [ 0, 0, 1, 0.8000002 ], "texture": "#1_0" },
				"south": { "uv": [ 0, 0, 1, 0.8000002 ], "texture": "#1_0" },
				"west": { "uv": [ 0, 0, 1, 0.8000002 ], "texture": "#1_0" },
				"east": { "uv": [ 0, 0, 1, 0.8000002 ], "texture": "#1_0" }
			}
		},
		{
			"__comment": "Element",
			"from": [ 7.8213, 4.65, 14.6213 ],
			"to": [ 8.0213, 7.15, 18.8213 ],
			"rotation": { "origin": [ -1.07868, 7, 9.32132 ], "axis": "y", "angle": 22.5 },
			"faces": {
				"down": { "uv": [ 0, 0, 0.5, 5.2 ], "texture": "#1_0", "rotation": 180 },
				"up": { "uv": [ 0, 0, 0.5, 5.2 ], "texture": "#1_0", "rotation": 180 },
				"north": { "uv": [ 0, 0, 0.5, 3 ], "texture": "#1_0" },
				"south": { "uv": [ 0, 0, 0.5, 3 ], "texture": "#1_0" },
				"west": { "uv": [ 0, 0, 5.2, 3 ], "texture": "#1_0" },
				"east": { "uv": [ 0, 0, 5.2, 3 ], "texture": "#1_0" }
			}
		},
		{
			"__comment": "Element",
			"from": [ 11.7213, 6.95, 14.6213 ],
			"to": [ 12.4213, 7.65, 18.8213 ],
			"rotation": { "origin": [ -1.07868, 6.6, 9.32132 ], "axis": "y", "angle": 22.5 },
			"faces": {
				"down": { "uv": [ 0, 0, 1, 4.2 ], "texture": "#1_0", "rotation": 180 },
				"up": { "uv": [ 0, 0, 1, 4.2 ], "texture": "#1_0", "rotation": 180 },
				"north": { "uv": [ 0, 0, 1, 0.8000002 ], "texture": "#1_0" },
				"south": { "uv": [ 0, 0, 1, 0.8000002 ], "texture": "#1_0" },
				"west": { "uv": [ 0, 0, 4.2, 0.8000002 ], "texture": "#1_0" },
				"east": { "uv": [ 0, 0, 4.2, 0.8000002 ], "texture": "#1_0" }
			}
		},
		{
			"__comment": "Element",
			"from": [ 7.3213, 6.95, 14.6213 ],
			"to": [ 8.0213, 7.65, 18.8213 ],
			"rotation": { "origin": [ -1.07868, 6.6, 9.32132 ], "axis": "y", "angle": 22.5 },
			"faces": {
				"down": { "uv": [ 0, 0, 1, 4.2 ], "texture": "#1_0", "rotation": 180 },
				"up": { "uv": [ 0, 0, 1, 4.2 ], "texture": "#1_0", "rotation": 180 },
				"north": { "uv": [ 0, 0, 1, 0.8000002 ], "texture": "#1_0" },
				"south": { "uv": [ 0, 0, 1, 0.8000002 ], "texture": "#1_0" },
				"west": { "uv": [ 0, 0, 4.2, 0.8000002 ], "texture": "#1_0" },
				"east": { "uv": [ 0, 0, 4.2, 0.8000002 ], "texture": "#1_0" }
			}
		},
		{
			"__comment": "Element",
			"from": [ 7.591, 5.1, 13.9688 ],
			"to": [ 12.391, 5.7, 14.5188 ],
			"rotation": { "origin": [ -0.45902, 7, 9.11877 ], "axis": "y", "angle": 22.5 },
			"faces": {
				"down": { "uv": [ 0, 0, 0.65, 6.3 ], "texture": "#1_0", "rotation": 90 },
				"up": { "uv": [ 0, 0, 0.65, 6.3 ], "texture": "#1_0", "rotation": 270 },
				"north": { "uv": [ 0, 0, 6.3, 0.6000004 ], "texture": "#1_0" },
				"south": { "uv": [ 0, 0, 6.3, 0.6000004 ], "texture": "#1_0" },
				"west": { "uv": [ 0, 0, 0.65, 0.6000004 ], "texture": "#1_0" },
				"east": { "uv": [ 0, 0, 0.65, 0.6000004 ], "texture": "#1_0" }
			}
		},
		{
			"__comment": "Element",
			"from": [ 7.6451, 0, 13.8381 ],
			"to": [ 12.4451, 0.6, 14.2881 ],
			"rotation": { "origin": [ -0.4049, 1.9, 8.98811 ], "axis": "y", "angle": 22.5 },
			"faces": {
				"down": { "uv": [ 0, 0, 0.65, 6.3 ], "texture": "#1_0", "rotation": 90 },
				"up": { "uv": [ 0, 0, 0.65, 6.3 ], "texture": "#1_0", "rotation": 270 },
				"north": { "uv": [ 0, 0, 6.3, 0.6000004 ], "texture": "#1_0" },
				"south": { "uv": [ 0, 0, 6.3, 0.6000004 ], "texture": "#1_0" },
				"west": { "uv": [ 0, 0, 0.65, 0.6000004 ], "texture": "#1_0" },
				"east": { "uv": [ 0, 0, 0.65, 0.6000004 ], "texture": "#1_0" }
			}
		},
		{
			"__comment": "Element",
			"from": [ 7.9213, 4.65, 14.6213 ],
			"to": [ 11.9213, 7.15, 14.6223 ],
			"rotation": { "origin": [ -1.07868, 7, 9.32132 ], "axis": "y", "angle": 22.5 },
			"faces": {
				"down": { "uv": [ 0, 0, 0.5, 4 ], "texture": "#1_0", "rotation": 90 },
				"up": { "uv": [ 0, 0, 0.5, 4 ], "texture": "#1_0", "rotation": 270 },
				"north": { "uv": [ 0, 0, 4, 3 ], "texture": "#1_0" },
				"south": { "uv": [ 0, 0, 4, 3 ], "texture": "#1_0" },
				"west": { "uv": [ 0, 0, 0.5, 3 ], "texture": "#1_0" },
				"east": { "uv": [ 0, 0, 0.5, 3 ], "texture": "#1_0" }
			}
		},
		{
			"__comment": "Element",
			"from": [ 7.9213, 6.95, 14.2213 ],
			"to": [ 11.9213, 7.65, 14.9213 ],
			"rotation": { "origin": [ -1.07868, 6.6, 9.32132 ], "axis": "y", "angle": 22.5 },
			"faces": {
				"down": { "uv": [ 0, 0, 1, 4 ], "texture": "#1_0", "rotation": 90 },
				"up": { "uv": [ 0, 0, 1, 4 ], "texture": "#1_0", "rotation": 270 },
				"north": { "uv": [ 0, 0, 4, 0.8000002 ], "texture": "#1_0" },
				"south": { "uv": [ 0, 0, 4, 0.8000002 ], "texture": "#1_0" },
				"west": { "uv": [ 0, 0, 1, 0.8000002 ], "texture": "#1_0" },
				"east": { "uv": [ 0, 0, 1, 0.8000002 ], "texture": "#1_0" }
			}
		},
		{
			"__comment": "Element",
			"from": [ 7.9213, 6.95, 18.5213 ],
			"to": [ 11.9213, 7.65, 19.3213 ],
			"rotation": { "origin": [ -1.07868, 6.6, 9.32132 ], "axis": "y", "angle": 22.5 },
			"faces": {
				"down": { "uv": [ 0, 0, 1, 4 ], "texture": "#1_0", "rotation": 90 },
				"up": { "uv": [ 0, 0, 1, 4 ], "texture": "#1_0", "rotation": 270 },
				"north": { "uv": [ 0, 0, 4, 0.8000002 ], "texture": "#1_0" },
				"south": { "uv": [ 0, 0, 4, 0.8000002 ], "texture": "#1_0" },
				"west": { "uv": [ 0, 0, 1, 0.8000002 ], "texture": "#1_0" },
				"east": { "uv": [ 0, 0, 1, 0.8000002 ], "texture": "#1_0" }
			}
		},
		{
			"__comment": "Element",
			"from": [ 7.9213, 4.65, 18.8213 ],
			"to": [ 11.9213, 7.15, 18.8223 ],
			"rotation": { "origin": [ -1.07868, 7, 9.32132 ], "axis": "y", "angle": 22.5 },
			"faces": {
				"down": { "uv": [ 0, 0, 0.5, 4 ], "texture": "#1_0", "rotation": 90 },
				"up": { "uv": [ 0, 0, 0.5, 4 ], "texture": "#1_0", "rotation": 270 },
				"north": { "uv": [ 0, 0, 4, 3 ], "texture": "#1_0" },
				"south": { "uv": [ 0, 0, 4, 3 ], "texture": "#1_0" },
				"west": { "uv": [ 0, 0, 0.5, 3 ], "texture": "#1_0" },
				"east": { "uv": [ 0, 0, 0.5, 3 ], "texture": "#1_0" }
			}
		},
		{
			"__comment": "Element",
			"from": [ 11.822, 0.25, 13.2736 ],
			"to": [ 12.822, 5.1, 13.3736 ],
			"rotation": { "origin": [ 0.02205, 6.9, 8.97362 ], "axis": "y", "angle": 22.5 },
			"faces": {
				"down": { "uv": [ 0, 0, 0.6, 6 ], "texture": "#1_0", "rotation": 90 },
				"up": { "uv": [ 0, 0, 0.6, 6 ], "texture": "#1_0", "rotation": 270 },
				"north": { "uv": [ 0, 0, 6, 5.75 ], "texture": "#1_0" },
				"south": { "uv": [ 0, 0, 6, 5.75 ], "texture": "#1_0" },
				"west": { "uv": [ 0, 0, 0.6, 5.75 ], "texture": "#1_0" },
				"east": { "uv": [ 0, 0, 0.6, 5.75 ], "texture": "#1_0" }
			}
		},
		{
			"__comment": "Element",
			"from": [ 7.4094, 5.1, 19.0127 ],
			"to": [ 12.0094, 5.7, 19.4627 ],
			"rotation": { "origin": [ -1.54062, 7, 9.51266 ], "axis": "y", "angle": 22.5 },
			"faces": {
				"down": { "uv": [ 0, 0, 0.65, 6.3 ], "texture": "#1_0", "rotation": 90 },
				"up": { "uv": [ 0, 0, 0.65, 6.3 ], "texture": "#1_0", "rotation": 270 },
				"north": { "uv": [ 0, 0, 6.3, 0.6000004 ], "texture": "#1_0" },
				"south": { "uv": [ 0, 0, 6.3, 0.6000004 ], "texture": "#1_0" },
				"west": { "uv": [ 0, 0, 0.65, 0.6000004 ], "texture": "#1_0" },
				"east": { "uv": [ 0, 0, 0.65, 0.6000004 ], "texture": "#1_0" }
			}
		},
		{
			"__comment": "Element",
			"from": [ 19.0104, 5.1, 11.9589 ],
			"to": [ 19.4604, 5.7, 16.4589 ],
			"rotation": { "origin": [ 9.51035, 7, 25.60889 ], "axis": "y", "angle": 22.5 },
			"faces": {
				"down": { "uv": [ 0, 0, 0.65, 6.3 ], "texture": "#1_0", "rotation": 180 },
				"up": { "uv": [ 0, 0, 0.65, 6.3 ], "texture": "#1_0", "rotation": 180 },
				"north": { "uv": [ 0, 0, 0.65, 0.6000004 ], "texture": "#1_0" },
				"south": { "uv": [ 0, 0, 0.65, 0.6000004 ], "texture": "#1_0" },
				"west": { "uv": [ 0, 0, 6.3, 0.6000004 ], "texture": "#1_0" },
				"east": { "uv": [ 0, 0, 6.3, 0.6000004 ], "texture": "#1_0" }
			}
		},
		{
			"__comment": "Element",
			"from": [ 7.706, 0, 18.8943 ],
			"to": [ 12.506, 0.6, 19.3443 ],
			"rotation": { "origin": [ -1.14401, 1.9, 9.29426 ], "axis": "y", "angle": 22.5 },
			"faces": {
				"down": { "uv": [ 0, 0, 0.65, 6.3 ], "texture": "#1_0", "rotation": 90 },
				"up": { "uv": [ 0, 0, 0.65, 6.3 ], "texture": "#1_0", "rotation": 270 },
				"north": { "uv": [ 0, 0, 6.3, 0.6000004 ], "texture": "#1_0" },
				"south": { "uv": [ 0, 0, 6.3, 0.6000004 ], "texture": "#1_0" },
				"west": { "uv": [ 0, 0, 0.65, 0.6000004 ], "texture": "#1_0" },
				"east": { "uv": [ 0, 0, 0.65, 0.6000004 ], "texture": "#1_0" }
			}
		},
		{
			"__comment": "Element",
			"from": [ 6.883, 0.25, 13.7289 ],
			"to": [ 12.783, 5.1, 19.7289 ],
			"rotation": { "origin": [ -1.11695, 6.9, 9.22893 ], "axis": "y", "angle": 22.5 },
			"faces": {
				"down": { "uv": [ 0, 0, 0.6, 6 ], "texture": "#1_0", "rotation": 90 },
				"up": { "uv": [ 0, 0, 0.6, 6 ], "texture": "#1_0", "rotation": 270 },
				"north": { "uv": [ 0, 0, 6, 5.75 ], "texture": "#1_0" },
				"south": { "uv": [ 0, 0, 6, 5.75 ], "texture": "#1_0" },
				"west": { "uv": [ 5, 2, 12.6, 8.75 ], "texture": "#1_0" },
				"east": { "uv": [ 2, 3, 8.6, 8.75 ], "texture": "#1_0" }
			}
		}
	],
	"display": {
		"thirdperson_righthand": {
			"rotation":  [ 75, 45, 0 ],
			"translation":  [ 0, 2.5, 0 ],
			"scale":  [ 0.375, 0.375, 0.375 ]
		},
		"thirdperson_lefthand": {
			"rotation":  [ 75, 45, 0 ],
			"translation":  [ 0, 2.5, 0 ],
			"scale":  [ 0.375, 0.375, 0.375 ]
		},
		"gui": {
			"rotation":  [ 45, 30, 0 ],
			"translation":  [ 0.0004, 0, 0 ],
			"scale":  [ 0.8, 0.708, 0.8 ]
		},
		"ground": {
			"translation":  [ 0, 5.5326, 0 ]
		},
		"fixed": {
			"rotation":  [ -90, -100, 0 ],
			"translation":  [ -0.695, -1.389, -14.31 ],
			"scale":  [ 2, 2, 2 ]
		}
	}
}